README.rst
setup.cfg
setup.py
zfs_utils_osx/__init__.py
zfs_utils_osx/argparse_utils.py
zfs_utils_osx/constants.py
zfs_utils_osx/load.py
zfs_utils_osx/main.py
zfs_utils_osx/metadata.py
zfs_utils_osx/utils.py
zfs_utils_osx/zpool.py
zfs_utils_osx.egg-info/PKG-INFO
zfs_utils_osx.egg-info/SOURCES.txt
zfs_utils_osx.egg-info/dependency_links.txt
zfs_utils_osx.egg-info/entry_points.txt
zfs_utils_osx.egg-info/top_level.txt