Metadata-Version: 1.1
Name: zfs-utils-osx
Version: 1.1.0
Summary: 
